<annotation>
	<folder></folder>
	<filename>express_co_uk_png.rf.11130c4987c41ec9d66c6cf7a9d39989.jpg</filename>
	<path>express_co_uk_png.rf.11130c4987c41ec9d66c6cf7a9d39989.jpg</path>
	<source>
		<database>roboflow.ai</database>
	</source>
	<size>
		<width>1024</width>
		<height>768</height>
		<depth>3</depth>
	</size>
	<segmented>0</segmented>
	<object>
		<name>text</name>
		<pose>Unspecified</pose>
		<truncated>0</truncated>
		<difficult>0</difficult>
		<occluded>0</occluded>
		<bndbox>
			<xmin>1</xmin>
			<xmax>1025</xmax>
			<ymin>1</ymin>
			<ymax>10</ymax>
		</bndbox>
	</object>
	<object>
		<name>heading</name>
		<pose>Unspecified</pose>
		<truncated>0</truncated>
		<difficult>0</difficult>
		<occluded>0</occluded>
		<bndbox>
			<xmin>43</xmin>
			<xmax>478</xmax>
			<ymin>35</ymin>
			<ymax>111</ymax>
		</bndbox>
	</object>
	<object>
		<name>button</name>
		<pose>Unspecified</pose>
		<truncated>0</truncated>
		<difficult>0</difficult>
		<occluded>0</occluded>
		<bndbox>
			<xmin>43</xmin>
			<xmax>481</xmax>
			<ymin>35</ymin>
			<ymax>111</ymax>
		</bndbox>
	</object>
	<object>
		<name>text</name>
		<pose>Unspecified</pose>
		<truncated>0</truncated>
		<difficult>0</difficult>
		<occluded>0</occluded>
		<bndbox>
			<xmin>918</xmin>
			<xmax>926</xmax>
			<ymin>52</ymin>
			<ymax>71</ymax>
		</bndbox>
	</object>
	<object>
		<name>button</name>
		<pose>Unspecified</pose>
		<truncated>0</truncated>
		<difficult>0</difficult>
		<occluded>0</occluded>
		<bndbox>
			<xmin>900</xmin>
			<xmax>983</xmax>
			<ymin>32</ymin>
			<ymax>83</ymax>
		</bndbox>
	</object>
	<object>
		<name>text</name>
		<pose>Unspecified</pose>
		<truncated>0</truncated>
		<difficult>0</difficult>
		<occluded>0</occluded>
		<bndbox>
			<xmin>926</xmin>
			<xmax>941</xmax>
			<ymin>52</ymin>
			<ymax>71</ymax>
		</bndbox>
	</object>
	<object>
		<name>button</name>
		<pose>Unspecified</pose>
		<truncated>0</truncated>
		<difficult>0</difficult>
		<occluded>0</occluded>
		<bndbox>
			<xmin>798</xmin>
			<xmax>821</xmax>
			<ymin>49</ymin>
			<ymax>72</ymax>
		</bndbox>
	</object>
	<object>
		<name>button</name>
		<pose>Unspecified</pose>
		<truncated>0</truncated>
		<difficult>0</difficult>
		<occluded>0</occluded>
		<bndbox>
			<xmin>835</xmin>
			<xmax>858</xmax>
			<ymin>49</ymin>
			<ymax>72</ymax>
		</bndbox>
	</object>
	<object>
		<name>button</name>
		<pose>Unspecified</pose>
		<truncated>0</truncated>
		<difficult>0</difficult>
		<occluded>0</occluded>
		<bndbox>
			<xmin>872</xmin>
			<xmax>895</xmax>
			<ymin>49</ymin>
			<ymax>72</ymax>
		</bndbox>
	</object>
	<object>
		<name>image</name>
		<pose>Unspecified</pose>
		<truncated>0</truncated>
		<difficult>0</difficult>
		<occluded>0</occluded>
		<bndbox>
			<xmin>760</xmin>
			<xmax>786</xmax>
			<ymin>47</ymin>
			<ymax>73</ymax>
		</bndbox>
	</object>
	<object>
		<name>button</name>
		<pose>Unspecified</pose>
		<truncated>0</truncated>
		<difficult>0</difficult>
		<occluded>0</occluded>
		<bndbox>
			<xmin>760</xmin>
			<xmax>786</xmax>
			<ymin>47</ymin>
			<ymax>73</ymax>
		</bndbox>
	</object>
	<object>
		<name>button</name>
		<pose>Unspecified</pose>
		<truncated>0</truncated>
		<difficult>0</difficult>
		<occluded>0</occluded>
		<bndbox>
			<xmin>567</xmin>
			<xmax>630</xmax>
			<ymin>48</ymin>
			<ymax>72</ymax>
		</bndbox>
	</object>
	<object>
		<name>button</name>
		<pose>Unspecified</pose>
		<truncated>0</truncated>
		<difficult>0</difficult>
		<occluded>0</occluded>
		<bndbox>
			<xmin>630</xmin>
			<xmax>714</xmax>
			<ymin>48</ymin>
			<ymax>72</ymax>
		</bndbox>
	</object>
	<object>
		<name>button</name>
		<pose>Unspecified</pose>
		<truncated>0</truncated>
		<difficult>0</difficult>
		<occluded>0</occluded>
		<bndbox>
			<xmin>591</xmin>
			<xmax>644</xmax>
			<ymin>88</ymin>
			<ymax>111</ymax>
		</bndbox>
	</object>
	<object>
		<name>button</name>
		<pose>Unspecified</pose>
		<truncated>0</truncated>
		<difficult>0</difficult>
		<occluded>0</occluded>
		<bndbox>
			<xmin>643</xmin>
			<xmax>712</xmax>
			<ymin>88</ymin>
			<ymax>111</ymax>
		</bndbox>
	</object>
	<object>
		<name>button</name>
		<pose>Unspecified</pose>
		<truncated>0</truncated>
		<difficult>0</difficult>
		<occluded>0</occluded>
		<bndbox>
			<xmin>711</xmin>
			<xmax>806</xmax>
			<ymin>88</ymin>
			<ymax>111</ymax>
		</bndbox>
	</object>
	<object>
		<name>button</name>
		<pose>Unspecified</pose>
		<truncated>0</truncated>
		<difficult>0</difficult>
		<occluded>0</occluded>
		<bndbox>
			<xmin>805</xmin>
			<xmax>889</xmax>
			<ymin>88</ymin>
			<ymax>111</ymax>
		</bndbox>
	</object>
	<object>
		<name>button</name>
		<pose>Unspecified</pose>
		<truncated>0</truncated>
		<difficult>0</difficult>
		<occluded>0</occluded>
		<bndbox>
			<xmin>888</xmin>
			<xmax>942</xmax>
			<ymin>88</ymin>
			<ymax>111</ymax>
		</bndbox>
	</object>
	<object>
		<name>button</name>
		<pose>Unspecified</pose>
		<truncated>0</truncated>
		<difficult>0</difficult>
		<occluded>0</occluded>
		<bndbox>
			<xmin>591</xmin>
			<xmax>639</xmax>
			<ymin>111</ymin>
			<ymax>134</ymax>
		</bndbox>
	</object>
	<object>
		<name>button</name>
		<pose>Unspecified</pose>
		<truncated>0</truncated>
		<difficult>0</difficult>
		<occluded>0</occluded>
		<bndbox>
			<xmin>43</xmin>
			<xmax>118</xmax>
			<ymin>126</ymin>
			<ymax>159</ymax>
		</bndbox>
	</object>
	<object>
		<name>button</name>
		<pose>Unspecified</pose>
		<truncated>0</truncated>
		<difficult>0</difficult>
		<occluded>0</occluded>
		<bndbox>
			<xmin>118</xmin>
			<xmax>191</xmax>
			<ymin>126</ymin>
			<ymax>159</ymax>
		</bndbox>
	</object>
	<object>
		<name>button</name>
		<pose>Unspecified</pose>
		<truncated>0</truncated>
		<difficult>0</difficult>
		<occluded>0</occluded>
		<bndbox>
			<xmin>191</xmin>
			<xmax>331</xmax>
			<ymin>126</ymin>
			<ymax>159</ymax>
		</bndbox>
	</object>
	<object>
		<name>button</name>
		<pose>Unspecified</pose>
		<truncated>0</truncated>
		<difficult>0</difficult>
		<occluded>0</occluded>
		<bndbox>
			<xmin>331</xmin>
			<xmax>407</xmax>
			<ymin>126</ymin>
			<ymax>159</ymax>
		</bndbox>
	</object>
	<object>
		<name>button</name>
		<pose>Unspecified</pose>
		<truncated>0</truncated>
		<difficult>0</difficult>
		<occluded>0</occluded>
		<bndbox>
			<xmin>407</xmin>
			<xmax>518</xmax>
			<ymin>126</ymin>
			<ymax>159</ymax>
		</bndbox>
	</object>
	<object>
		<name>button</name>
		<pose>Unspecified</pose>
		<truncated>0</truncated>
		<difficult>0</difficult>
		<occluded>0</occluded>
		<bndbox>
			<xmin>518</xmin>
			<xmax>614</xmax>
			<ymin>126</ymin>
			<ymax>159</ymax>
		</bndbox>
	</object>
	<object>
		<name>button</name>
		<pose>Unspecified</pose>
		<truncated>0</truncated>
		<difficult>0</difficult>
		<occluded>0</occluded>
		<bndbox>
			<xmin>614</xmin>
			<xmax>698</xmax>
			<ymin>126</ymin>
			<ymax>159</ymax>
		</bndbox>
	</object>
	<object>
		<name>button</name>
		<pose>Unspecified</pose>
		<truncated>0</truncated>
		<difficult>0</difficult>
		<occluded>0</occluded>
		<bndbox>
			<xmin>698</xmin>
			<xmax>860</xmax>
			<ymin>126</ymin>
			<ymax>159</ymax>
		</bndbox>
	</object>
	<object>
		<name>button</name>
		<pose>Unspecified</pose>
		<truncated>0</truncated>
		<difficult>0</difficult>
		<occluded>0</occluded>
		<bndbox>
			<xmin>860</xmin>
			<xmax>983</xmax>
			<ymin>126</ymin>
			<ymax>159</ymax>
		</bndbox>
	</object>
	<object>
		<name>text</name>
		<pose>Unspecified</pose>
		<truncated>0</truncated>
		<difficult>0</difficult>
		<occluded>0</occluded>
		<bndbox>
			<xmin>44</xmin>
			<xmax>119</xmax>
			<ymin>159</ymin>
			<ymax>185</ymax>
		</bndbox>
	</object>
	<object>
		<name>link</name>
		<pose>Unspecified</pose>
		<truncated>0</truncated>
		<difficult>0</difficult>
		<occluded>0</occluded>
		<bndbox>
			<xmin>136</xmin>
			<xmax>227</xmax>
			<ymin>166</ymin>
			<ymax>180</ymax>
		</bndbox>
	</object>
	<object>
		<name>text</name>
		<pose>Unspecified</pose>
		<truncated>0</truncated>
		<difficult>0</difficult>
		<occluded>0</occluded>
		<bndbox>
			<xmin>227</xmin>
			<xmax>248</xmax>
			<ymin>165</ymin>
			<ymax>182</ymax>
		</bndbox>
	</object>
	<object>
		<name>link</name>
		<pose>Unspecified</pose>
		<truncated>0</truncated>
		<difficult>0</difficult>
		<occluded>0</occluded>
		<bndbox>
			<xmin>252</xmin>
			<xmax>330</xmax>
			<ymin>166</ymin>
			<ymax>180</ymax>
		</bndbox>
	</object>
	<object>
		<name>text</name>
		<pose>Unspecified</pose>
		<truncated>0</truncated>
		<difficult>0</difficult>
		<occluded>0</occluded>
		<bndbox>
			<xmin>329</xmin>
			<xmax>350</xmax>
			<ymin>165</ymin>
			<ymax>182</ymax>
		</bndbox>
	</object>
	<object>
		<name>link</name>
		<pose>Unspecified</pose>
		<truncated>0</truncated>
		<difficult>0</difficult>
		<occluded>0</occluded>
		<bndbox>
			<xmin>354</xmin>
			<xmax>443</xmax>
			<ymin>166</ymin>
			<ymax>180</ymax>
		</bndbox>
	</object>
	<object>
		<name>text</name>
		<pose>Unspecified</pose>
		<truncated>0</truncated>
		<difficult>0</difficult>
		<occluded>0</occluded>
		<bndbox>
			<xmin>442</xmin>
			<xmax>463</xmax>
			<ymin>165</ymin>
			<ymax>182</ymax>
		</bndbox>
	</object>
	<object>
		<name>link</name>
		<pose>Unspecified</pose>
		<truncated>0</truncated>
		<difficult>0</difficult>
		<occluded>0</occluded>
		<bndbox>
			<xmin>467</xmin>
			<xmax>548</xmax>
			<ymin>166</ymin>
			<ymax>180</ymax>
		</bndbox>
	</object>
	<object>
		<name>text</name>
		<pose>Unspecified</pose>
		<truncated>0</truncated>
		<difficult>0</difficult>
		<occluded>0</occluded>
		<bndbox>
			<xmin>546</xmin>
			<xmax>567</xmax>
			<ymin>165</ymin>
			<ymax>182</ymax>
		</bndbox>
	</object>
	<object>
		<name>link</name>
		<pose>Unspecified</pose>
		<truncated>0</truncated>
		<difficult>0</difficult>
		<occluded>0</occluded>
		<bndbox>
			<xmin>571</xmin>
			<xmax>658</xmax>
			<ymin>166</ymin>
			<ymax>180</ymax>
		</bndbox>
	</object>
	<object>
		<name>text</name>
		<pose>Unspecified</pose>
		<truncated>0</truncated>
		<difficult>0</difficult>
		<occluded>0</occluded>
		<bndbox>
			<xmin>657</xmin>
			<xmax>678</xmax>
			<ymin>165</ymin>
			<ymax>182</ymax>
		</bndbox>
	</object>
	<object>
		<name>link</name>
		<pose>Unspecified</pose>
		<truncated>0</truncated>
		<difficult>0</difficult>
		<occluded>0</occluded>
		<bndbox>
			<xmin>682</xmin>
			<xmax>731</xmax>
			<ymin>166</ymin>
			<ymax>180</ymax>
		</bndbox>
	</object>
	<object>
		<name>text</name>
		<pose>Unspecified</pose>
		<truncated>0</truncated>
		<difficult>0</difficult>
		<occluded>0</occluded>
		<bndbox>
			<xmin>731</xmin>
			<xmax>752</xmax>
			<ymin>165</ymin>
			<ymax>182</ymax>
		</bndbox>
	</object>
	<object>
		<name>link</name>
		<pose>Unspecified</pose>
		<truncated>0</truncated>
		<difficult>0</difficult>
		<occluded>0</occluded>
		<bndbox>
			<xmin>756</xmin>
			<xmax>832</xmax>
			<ymin>166</ymin>
			<ymax>180</ymax>
		</bndbox>
	</object>
	<object>
		<name>text</name>
		<pose>Unspecified</pose>
		<truncated>0</truncated>
		<difficult>0</difficult>
		<occluded>0</occluded>
		<bndbox>
			<xmin>830</xmin>
			<xmax>851</xmax>
			<ymin>165</ymin>
			<ymax>182</ymax>
		</bndbox>
	</object>
	<object>
		<name>link</name>
		<pose>Unspecified</pose>
		<truncated>0</truncated>
		<difficult>0</difficult>
		<occluded>0</occluded>
		<bndbox>
			<xmin>855</xmin>
			<xmax>939</xmax>
			<ymin>166</ymin>
			<ymax>180</ymax>
		</bndbox>
	</object>
	<object>
		<name>text</name>
		<pose>Unspecified</pose>
		<truncated>0</truncated>
		<difficult>0</difficult>
		<occluded>0</occluded>
		<bndbox>
			<xmin>939</xmin>
			<xmax>960</xmax>
			<ymin>165</ymin>
			<ymax>182</ymax>
		</bndbox>
	</object>
	<object>
		<name>link</name>
		<pose>Unspecified</pose>
		<truncated>0</truncated>
		<difficult>0</difficult>
		<occluded>0</occluded>
		<bndbox>
			<xmin>49</xmin>
			<xmax>85</xmax>
			<ymin>192</ymin>
			<ymax>206</ymax>
		</bndbox>
	</object>
	<object>
		<name>text</name>
		<pose>Unspecified</pose>
		<truncated>0</truncated>
		<difficult>0</difficult>
		<occluded>0</occluded>
		<bndbox>
			<xmin>85</xmin>
			<xmax>106</xmax>
			<ymin>191</ymin>
			<ymax>208</ymax>
		</bndbox>
	</object>
	<object>
		<name>link</name>
		<pose>Unspecified</pose>
		<truncated>0</truncated>
		<difficult>0</difficult>
		<occluded>0</occluded>
		<bndbox>
			<xmin>110</xmin>
			<xmax>136</xmax>
			<ymin>192</ymin>
			<ymax>206</ymax>
		</bndbox>
	</object>
	<object>
		<name>image</name>
		<pose>Unspecified</pose>
		<truncated>0</truncated>
		<difficult>0</difficult>
		<occluded>0</occluded>
		<bndbox>
			<xmin>43</xmin>
			<xmax>633</xmax>
			<ymin>204</ymin>
			<ymax>554</ymax>
		</bndbox>
	</object>
	<object>
		<name>button</name>
		<pose>Unspecified</pose>
		<truncated>0</truncated>
		<difficult>0</difficult>
		<occluded>0</occluded>
		<bndbox>
			<xmin>983</xmin>
			<xmax>983</xmax>
			<ymin>204</ymin>
			<ymax>204</ymax>
		</bndbox>
	</object>
	<object>
		<name>heading</name>
		<pose>Unspecified</pose>
		<truncated>0</truncated>
		<difficult>0</difficult>
		<occluded>0</occluded>
		<bndbox>
			<xmin>653</xmin>
			<xmax>983</xmax>
			<ymin>203</ymin>
			<ymax>554</ymax>
		</bndbox>
	</object>
	<object>
		<name>link</name>
		<pose>Unspecified</pose>
		<truncated>0</truncated>
		<difficult>0</difficult>
		<occluded>0</occluded>
		<bndbox>
			<xmin>653</xmin>
			<xmax>983</xmax>
			<ymin>306</ymin>
			<ymax>351</ymax>
		</bndbox>
	</object>
	<object>
		<name>image</name>
		<pose>Unspecified</pose>
		<truncated>0</truncated>
		<difficult>0</difficult>
		<occluded>0</occluded>
		<bndbox>
			<xmin>653</xmin>
			<xmax>836</xmax>
			<ymin>420</ymin>
			<ymax>542</ymax>
		</bndbox>
	</object>
	<object>
		<name>button</name>
		<pose>Unspecified</pose>
		<truncated>0</truncated>
		<difficult>0</difficult>
		<occluded>0</occluded>
		<bndbox>
			<xmin>653</xmin>
			<xmax>983</xmax>
			<ymin>420</ymin>
			<ymax>542</ymax>
		</bndbox>
	</object>
	<object>
		<name>heading</name>
		<pose>Unspecified</pose>
		<truncated>0</truncated>
		<difficult>0</difficult>
		<occluded>0</occluded>
		<bndbox>
			<xmin>846</xmin>
			<xmax>983</xmax>
			<ymin>426</ymin>
			<ymax>511</ymax>
		</bndbox>
	</object>
	<object>
		<name>image</name>
		<pose>Unspecified</pose>
		<truncated>0</truncated>
		<difficult>0</difficult>
		<occluded>0</occluded>
		<bndbox>
			<xmin>43</xmin>
			<xmax>225</xmax>
			<ymin>569</ymin>
			<ymax>691</ymax>
		</bndbox>
	</object>
	<object>
		<name>button</name>
		<pose>Unspecified</pose>
		<truncated>0</truncated>
		<difficult>0</difficult>
		<occluded>0</occluded>
		<bndbox>
			<xmin>43</xmin>
			<xmax>225</xmax>
			<ymin>569</ymin>
			<ymax>769</ymax>
		</bndbox>
	</object>
	<object>
		<name>heading</name>
		<pose>Unspecified</pose>
		<truncated>0</truncated>
		<difficult>0</difficult>
		<occluded>0</occluded>
		<bndbox>
			<xmin>43</xmin>
			<xmax>225</xmax>
			<ymin>697</ymin>
			<ymax>769</ymax>
		</bndbox>
	</object>
	<object>
		<name>image</name>
		<pose>Unspecified</pose>
		<truncated>0</truncated>
		<difficult>0</difficult>
		<occluded>0</occluded>
		<bndbox>
			<xmin>245</xmin>
			<xmax>427</xmax>
			<ymin>569</ymin>
			<ymax>691</ymax>
		</bndbox>
	</object>
	<object>
		<name>button</name>
		<pose>Unspecified</pose>
		<truncated>0</truncated>
		<difficult>0</difficult>
		<occluded>0</occluded>
		<bndbox>
			<xmin>245</xmin>
			<xmax>427</xmax>
			<ymin>569</ymin>
			<ymax>769</ymax>
		</bndbox>
	</object>
	<object>
		<name>heading</name>
		<pose>Unspecified</pose>
		<truncated>0</truncated>
		<difficult>0</difficult>
		<occluded>0</occluded>
		<bndbox>
			<xmin>245</xmin>
			<xmax>427</xmax>
			<ymin>697</ymin>
			<ymax>769</ymax>
		</bndbox>
	</object>
	<object>
		<name>image</name>
		<pose>Unspecified</pose>
		<truncated>0</truncated>
		<difficult>0</difficult>
		<occluded>0</occluded>
		<bndbox>
			<xmin>447</xmin>
			<xmax>629</xmax>
			<ymin>569</ymin>
			<ymax>691</ymax>
		</bndbox>
	</object>
	<object>
		<name>button</name>
		<pose>Unspecified</pose>
		<truncated>0</truncated>
		<difficult>0</difficult>
		<occluded>0</occluded>
		<bndbox>
			<xmin>447</xmin>
			<xmax>629</xmax>
			<ymin>569</ymin>
			<ymax>769</ymax>
		</bndbox>
	</object>
	<object>
		<name>heading</name>
		<pose>Unspecified</pose>
		<truncated>0</truncated>
		<difficult>0</difficult>
		<occluded>0</occluded>
		<bndbox>
			<xmin>447</xmin>
			<xmax>629</xmax>
			<ymin>697</ymin>
			<ymax>769</ymax>
		</bndbox>
	</object>
	<object>
		<name>text</name>
		<pose>Unspecified</pose>
		<truncated>0</truncated>
		<difficult>0</difficult>
		<occluded>0</occluded>
		<bndbox>
			<xmin>653</xmin>
			<xmax>983</xmax>
			<ymin>569</ymin>
			<ymax>590</ymax>
		</bndbox>
	</object>
	<object>
		<name>iframe</name>
		<pose>Unspecified</pose>
		<truncated>0</truncated>
		<difficult>0</difficult>
		<occluded>0</occluded>
		<bndbox>
			<xmin>353</xmin>
			<xmax>673</xmax>
			<ymin>719</ymin>
			<ymax>769</ymax>
		</bndbox>
	</object>
</annotation>
