<annotation>
	<folder></folder>
	<filename>oracle_com_png.rf.cf67bf84cc9996dc031ce83ac01fea26.jpg</filename>
	<path>oracle_com_png.rf.cf67bf84cc9996dc031ce83ac01fea26.jpg</path>
	<source>
		<database>roboflow.ai</database>
	</source>
	<size>
		<width>1024</width>
		<height>768</height>
		<depth>3</depth>
	</size>
	<segmented>0</segmented>
	<object>
		<name>button</name>
		<pose>Unspecified</pose>
		<truncated>0</truncated>
		<difficult>0</difficult>
		<occluded>0</occluded>
		<bndbox>
			<xmin>17</xmin>
			<xmax>61</xmax>
			<ymin>11</ymin>
			<ymax>55</ymax>
		</bndbox>
	</object>
	<object>
		<name>button</name>
		<pose>Unspecified</pose>
		<truncated>0</truncated>
		<difficult>0</difficult>
		<occluded>0</occluded>
		<bndbox>
			<xmin>61</xmin>
			<xmax>105</xmax>
			<ymin>9</ymin>
			<ymax>53</ymax>
		</bndbox>
	</object>
	<object>
		<name>button</name>
		<pose>Unspecified</pose>
		<truncated>0</truncated>
		<difficult>0</difficult>
		<occluded>0</occluded>
		<bndbox>
			<xmin>110</xmin>
			<xmax>152</xmax>
			<ymin>12</ymin>
			<ymax>50</ymax>
		</bndbox>
	</object>
	<object>
		<name>field</name>
		<pose>Unspecified</pose>
		<truncated>0</truncated>
		<difficult>0</difficult>
		<occluded>0</occluded>
		<bndbox>
			<xmin>151</xmin>
			<xmax>949</xmax>
			<ymin>12</ymin>
			<ymax>50</ymax>
		</bndbox>
	</object>
	<object>
		<name>text</name>
		<pose>Unspecified</pose>
		<truncated>0</truncated>
		<difficult>0</difficult>
		<occluded>0</occluded>
		<bndbox>
			<xmin>151</xmin>
			<xmax>653</xmax>
			<ymin>19</ymin>
			<ymax>41</ymax>
		</bndbox>
	</object>
	<object>
		<name>button</name>
		<pose>Unspecified</pose>
		<truncated>0</truncated>
		<difficult>0</difficult>
		<occluded>0</occluded>
		<bndbox>
			<xmin>958</xmin>
			<xmax>997</xmax>
			<ymin>11</ymin>
			<ymax>51</ymax>
		</bndbox>
	</object>
	<object>
		<name>heading</name>
		<pose>Unspecified</pose>
		<truncated>0</truncated>
		<difficult>0</difficult>
		<occluded>0</occluded>
		<bndbox>
			<xmin>39</xmin>
			<xmax>173</xmax>
			<ymin>283</ymin>
			<ymax>316</ymax>
		</bndbox>
	</object>
	<object>
		<name>button</name>
		<pose>Unspecified</pose>
		<truncated>0</truncated>
		<difficult>0</difficult>
		<occluded>0</occluded>
		<bndbox>
			<xmin>39</xmin>
			<xmax>301</xmax>
			<ymin>283</ymin>
			<ymax>505</ymax>
		</bndbox>
	</object>
	<object>
		<name>heading</name>
		<pose>Unspecified</pose>
		<truncated>0</truncated>
		<difficult>0</difficult>
		<occluded>0</occluded>
		<bndbox>
			<xmin>39</xmin>
			<xmax>301</xmax>
			<ymin>315</ymin>
			<ymax>353</ymax>
		</bndbox>
	</object>
	<object>
		<name>text</name>
		<pose>Unspecified</pose>
		<truncated>0</truncated>
		<difficult>0</difficult>
		<occluded>0</occluded>
		<bndbox>
			<xmin>39</xmin>
			<xmax>301</xmax>
			<ymin>368</ymin>
			<ymax>388</ymax>
		</bndbox>
	</object>
	<object>
		<name>text</name>
		<pose>Unspecified</pose>
		<truncated>0</truncated>
		<difficult>0</difficult>
		<occluded>0</occluded>
		<bndbox>
			<xmin>39</xmin>
			<xmax>301</xmax>
			<ymin>393</ymin>
			<ymax>489</ymax>
		</bndbox>
	</object>
	<object>
		<name>heading</name>
		<pose>Unspecified</pose>
		<truncated>0</truncated>
		<difficult>0</difficult>
		<occluded>0</occluded>
		<bndbox>
			<xmin>380</xmin>
			<xmax>444</xmax>
			<ymin>283</ymin>
			<ymax>316</ymax>
		</bndbox>
	</object>
	<object>
		<name>button</name>
		<pose>Unspecified</pose>
		<truncated>0</truncated>
		<difficult>0</difficult>
		<occluded>0</occluded>
		<bndbox>
			<xmin>380</xmin>
			<xmax>642</xmax>
			<ymin>283</ymin>
			<ymax>486</ymax>
		</bndbox>
	</object>
	<object>
		<name>heading</name>
		<pose>Unspecified</pose>
		<truncated>0</truncated>
		<difficult>0</difficult>
		<occluded>0</occluded>
		<bndbox>
			<xmin>380</xmin>
			<xmax>642</xmax>
			<ymin>315</ymin>
			<ymax>353</ymax>
		</bndbox>
	</object>
	<object>
		<name>text</name>
		<pose>Unspecified</pose>
		<truncated>0</truncated>
		<difficult>0</difficult>
		<occluded>0</occluded>
		<bndbox>
			<xmin>380</xmin>
			<xmax>642</xmax>
			<ymin>368</ymin>
			<ymax>388</ymax>
		</bndbox>
	</object>
	<object>
		<name>text</name>
		<pose>Unspecified</pose>
		<truncated>0</truncated>
		<difficult>0</difficult>
		<occluded>0</occluded>
		<bndbox>
			<xmin>380</xmin>
			<xmax>642</xmax>
			<ymin>393</ymin>
			<ymax>470</ymax>
		</bndbox>
	</object>
	<object>
		<name>heading</name>
		<pose>Unspecified</pose>
		<truncated>0</truncated>
		<difficult>0</difficult>
		<occluded>0</occluded>
		<bndbox>
			<xmin>722</xmin>
			<xmax>984</xmax>
			<ymin>283</ymin>
			<ymax>412</ymax>
		</bndbox>
	</object>
	<object>
		<name>text</name>
		<pose>Unspecified</pose>
		<truncated>0</truncated>
		<difficult>0</difficult>
		<occluded>0</occluded>
		<bndbox>
			<xmin>722</xmin>
			<xmax>984</xmax>
			<ymin>427</ymin>
			<ymax>504</ymax>
		</bndbox>
	</object>
	<object>
		<name>link</name>
		<pose>Unspecified</pose>
		<truncated>0</truncated>
		<difficult>0</difficult>
		<occluded>0</occluded>
		<bndbox>
			<xmin>744</xmin>
			<xmax>859</xmax>
			<ymin>527</ymin>
			<ymax>544</ymax>
		</bndbox>
	</object>
	<object>
		<name>link</name>
		<pose>Unspecified</pose>
		<truncated>0</truncated>
		<difficult>0</difficult>
		<occluded>0</occluded>
		<bndbox>
			<xmin>744</xmin>
			<xmax>851</xmax>
			<ymin>575</ymin>
			<ymax>591</ymax>
		</bndbox>
	</object>
	<object>
		<name>link</name>
		<pose>Unspecified</pose>
		<truncated>0</truncated>
		<difficult>0</difficult>
		<occluded>0</occluded>
		<bndbox>
			<xmin>717</xmin>
			<xmax>746</xmax>
			<ymin>698</ymin>
			<ymax>709</ymax>
		</bndbox>
	</object>
	<object>
		<name>button</name>
		<pose>Unspecified</pose>
		<truncated>0</truncated>
		<difficult>0</difficult>
		<occluded>0</occluded>
		<bndbox>
			<xmin>717</xmin>
			<xmax>746</xmax>
			<ymin>691</ymin>
			<ymax>716</ymax>
		</bndbox>
	</object>
	<object>
		<name>link</name>
		<pose>Unspecified</pose>
		<truncated>0</truncated>
		<difficult>0</difficult>
		<occluded>0</occluded>
		<bndbox>
			<xmin>757</xmin>
			<xmax>786</xmax>
			<ymin>698</ymin>
			<ymax>709</ymax>
		</bndbox>
	</object>
	<object>
		<name>button</name>
		<pose>Unspecified</pose>
		<truncated>0</truncated>
		<difficult>0</difficult>
		<occluded>0</occluded>
		<bndbox>
			<xmin>757</xmin>
			<xmax>786</xmax>
			<ymin>691</ymin>
			<ymax>716</ymax>
		</bndbox>
	</object>
	<object>
		<name>link</name>
		<pose>Unspecified</pose>
		<truncated>0</truncated>
		<difficult>0</difficult>
		<occluded>0</occluded>
		<bndbox>
			<xmin>797</xmin>
			<xmax>826</xmax>
			<ymin>698</ymin>
			<ymax>709</ymax>
		</bndbox>
	</object>
	<object>
		<name>button</name>
		<pose>Unspecified</pose>
		<truncated>0</truncated>
		<difficult>0</difficult>
		<occluded>0</occluded>
		<bndbox>
			<xmin>797</xmin>
			<xmax>826</xmax>
			<ymin>691</ymin>
			<ymax>716</ymax>
		</bndbox>
	</object>
	<object>
		<name>link</name>
		<pose>Unspecified</pose>
		<truncated>0</truncated>
		<difficult>0</difficult>
		<occluded>0</occluded>
		<bndbox>
			<xmin>837</xmin>
			<xmax>866</xmax>
			<ymin>698</ymin>
			<ymax>709</ymax>
		</bndbox>
	</object>
	<object>
		<name>button</name>
		<pose>Unspecified</pose>
		<truncated>0</truncated>
		<difficult>0</difficult>
		<occluded>0</occluded>
		<bndbox>
			<xmin>837</xmin>
			<xmax>866</xmax>
			<ymin>691</ymin>
			<ymax>716</ymax>
		</bndbox>
	</object>
	<object>
		<name>link</name>
		<pose>Unspecified</pose>
		<truncated>0</truncated>
		<difficult>0</difficult>
		<occluded>0</occluded>
		<bndbox>
			<xmin>877</xmin>
			<xmax>906</xmax>
			<ymin>698</ymin>
			<ymax>709</ymax>
		</bndbox>
	</object>
	<object>
		<name>button</name>
		<pose>Unspecified</pose>
		<truncated>0</truncated>
		<difficult>0</difficult>
		<occluded>0</occluded>
		<bndbox>
			<xmin>877</xmin>
			<xmax>906</xmax>
			<ymin>691</ymin>
			<ymax>716</ymax>
		</bndbox>
	</object>
</annotation>
